services/__init__.py
services/file_handler.py
services/html_parser.py
services/json_converter.py
utils/__init__.py
utils/logger.py
html_table_to_json-0.1.0.dist-info/LICENSE.md
html_table_to_json-0.1.0.dist-info/METADATA
html_table_to_json-0.1.0.dist-info/WHEEL
html_table_to_json-0.1.0.dist-info/entry_points.txt
html_table_to_json-0.1.0.dist-info/top_level.txt
html_table_to_json-0.1.0.dist-info/RECORD
