Metadata-Version: 2.1
Name: html-table-to-json
Version: 0.1.0
Summary: Effortlessly convert HTML tables to JSON with this Python-based tool.
Home-page: https://github.com/ThiagoSchumann/html-table-to-json
Author: Thiago Schumann
Author-email: thiagoarturschumann@gmail.com
License: UNKNOWN
Platform: UNKNOWN
Classifier: Programming Language :: Python :: 3
Classifier: License :: OSI Approved :: MIT License
Classifier: Operating System :: OS Independent
Requires-Python: >=3.6
License-File: LICENSE.md
Requires-Dist: beautifulsoup4
Requires-Dist: pandas
